SnowML/__init__.py
SnowML/analysis/__init__.py
SnowML/bayesian/__init__.py
SnowML/bayesian/base.py
SnowML/bayesian/beta.py
SnowML/bayesian/compare.py
SnowML/bayesian/gamma.py
SnowML/bayesian/normal.py
SnowML/evaluation/__init__.py
SnowML/evaluation/evaluation_utils.py
SnowML/evaluation/evaluators.py
SnowML/model_logging/__init__.py
SnowML/model_logging/mlflow/__init__.py
SnowML/model_logging/mlflow/register_model.py
SnowML/notifications/__init__.py
SnowML/notifications/notifications.py
SnowML/preprocessing/__init__.py
SnowML/utils/__init__.py
SnowML/utils/aws.py
SnowML/utils/huggingface.py
SnowML/utils/pandas.py
SnowML/utils/pyspark.py
SnowML/utils/regex.py
SnowML/utils/notifications/__init__.py
SnowML/utils/notifications/_email.py
SnowML/utils/notifications/_slack.py
SnowML-0.2.0.dist-info/LICENSE
SnowML-0.2.0.dist-info/METADATA
SnowML-0.2.0.dist-info/WHEEL
SnowML-0.2.0.dist-info/top_level.txt
SnowML-0.2.0.dist-info/RECORD
