Metadata-Version: 2.1
Name: SnowML
Version: 0.2.0
Summary: Openweb's ML utility package
Home-page: https://github.com/SpotIM/openweb-ml-utils
Author: Shlomi Green
Author-email: Shlomi.G@openweb.com
Maintainer: Shlomi Green
License: MIT
Classifier: Programming Language :: Python :: 3
Classifier: Programming Language :: Python :: 3.6
Classifier: Programming Language :: Python :: 3.7
Classifier: Programming Language :: Python :: 3.8
Classifier: Programming Language :: Python :: 3.9
Classifier: Programming Language :: Python :: 3.10
Classifier: License :: OSI Approved :: MIT License
Classifier: Operating System :: OS Independent
License-File: LICENSE
Requires-Dist: pandas
Requires-Dist: scikit-learn
Requires-Dist: numpy
Requires-Dist: slack-sdk
Requires-Dist: mlflow
Requires-Dist: scipy
Requires-Dist: pyspark
